.travis.yml
MANIFEST.in
README.txt
TODO.txt
bootstrap.py
buildout.cfg
setup.cfg
setup.py
test-4.0.x.cfg
test-4.1.x.cfg
test-4.2.x.cfg
test-4.3.x.cfg
docs/HISTORY.txt
quintagroup/__init__.py
quintagroup.transmogrifier.egg-info/PKG-INFO
quintagroup.transmogrifier.egg-info/SOURCES.txt
quintagroup.transmogrifier.egg-info/dependency_links.txt
quintagroup.transmogrifier.egg-info/entry_points.txt
quintagroup.transmogrifier.egg-info/namespace_packages.txt
quintagroup.transmogrifier.egg-info/not-zip-safe
quintagroup.transmogrifier.egg-info/requires.txt
quintagroup.transmogrifier.egg-info/top_level.txt
quintagroup/transmogrifier/__init__.py
quintagroup/transmogrifier/binary.py
quintagroup/transmogrifier/catalogsource.py
quintagroup/transmogrifier/comments.py
quintagroup/transmogrifier/configure.zcml
quintagroup/transmogrifier/configview.py
quintagroup/transmogrifier/datacorrector.py
quintagroup/transmogrifier/export.cfg
quintagroup/transmogrifier/exportimport.py
quintagroup/transmogrifier/flushcache.py
quintagroup/transmogrifier/import.cfg
quintagroup/transmogrifier/interfacemanager.py
quintagroup/transmogrifier/interfaces.py
quintagroup/transmogrifier/logger.py
quintagroup/transmogrifier/manifest.py
quintagroup/transmogrifier/marshall.py
quintagroup/transmogrifier/meta.zcml
quintagroup/transmogrifier/ordereddict.py
quintagroup/transmogrifier/patches.py
quintagroup/transmogrifier/pipelineconfig.pt
quintagroup/transmogrifier/portlets.py
quintagroup/transmogrifier/propertymanager.py
quintagroup/transmogrifier/reader.py
quintagroup/transmogrifier/references.py
quintagroup/transmogrifier/sitewalker.py
quintagroup/transmogrifier/substitution.py
quintagroup/transmogrifier/testing.py
quintagroup/transmogrifier/testing.zcml
quintagroup/transmogrifier/writer.py
quintagroup/transmogrifier/xslt.py
quintagroup/transmogrifier/adapters/__init__.py
quintagroup/transmogrifier/adapters/configure.zcml
quintagroup/transmogrifier/adapters/exporting.py
quintagroup/transmogrifier/adapters/importing.py
quintagroup/transmogrifier/namespaces/__init__.py
quintagroup/transmogrifier/namespaces/atns.py
quintagroup/transmogrifier/namespaces/cmfns.py
quintagroup/transmogrifier/namespaces/dcns.py
quintagroup/transmogrifier/namespaces/util.py
quintagroup/transmogrifier/profiles/default/controlpanel.xml
quintagroup/transmogrifier/profiles/default/metadata.xml
