Metadata-Version: 1.0
Name: quintagroup.transmogrifier
Version: 0.5
Summary: Plone blueprints for collective.transmogrifier pipelines.
Home-page: http://quintagroup.com
Author: Quintagroup
Author-email: info@quintagroup.com
License: GPL
Platform: UNKNOWN
Classifier: Framework :: Zope2
Classifier: Framework :: Zope3
Classifier: Framework :: Plone
Classifier: Framework :: Plone :: 4.0
Classifier: Framework :: Plone :: 4.1
Classifier: Framework :: Plone :: 4.2
Classifier: Framework :: Plone :: 4.3
Classifier: Programming Language :: Python
Classifier: Intended Audience :: Developers
Classifier: Natural Language :: English
Classifier: Operating System :: OS Independent
Classifier: Topic :: Internet :: WWW/HTTP :: Dynamic Content
Classifier: Topic :: Software Development :: Libraries :: Application Frameworks
Classifier: Topic :: Software Development :: Libraries :: Python Modules
Classifier: License :: OSI Approved :: GNU General Public License (GPL)
